pbssh/__init__.py
pbssh/__main__.py
pbssh/pbssh.py
pbssh-0.1.7.dist-info/LICENSE
pbssh-0.1.7.dist-info/METADATA
pbssh-0.1.7.dist-info/WHEEL
pbssh-0.1.7.dist-info/entry_points.txt
pbssh-0.1.7.dist-info/top_level.txt
pbssh-0.1.7.dist-info/RECORD
